[
  {
    "Company":"ABBEYBDS",
    "Prev_Close":10.1,
    "Opening_Price":10.1,
    "High":0.0,
    "Low":0.0,
    "Close":0.0,
    "Change":0.0,
    "Trades":239.0,
    "Volume":516112.0,
    "Value":4955990.25,
    "Trade_Date":"22 Jun 26",
    "Pct_Change":0.0,
    "Fetched_At":"2026-06-22 12:57:23"
  },
  {
    "Company":"ABCTRANS",
    "Prev_Close":7.8,
    "Opening_Price":7.8,
    "High":0.0,
    "Low":0.0,
    "Close":0.0,
    "Change":0.0,
    "Trades":190.0,
    "Volume":271406.0,
    "Value":1946800.0,
    "Trade_Date":"22 Jun 26",
    "Pct_Change":0.0,
    "Fetched_At":"2026-06-22 12:57:23"
  },
  {
    "Company":"ACADEMY",
    "Prev_Close":8.1,
    "Opening_Price":8.1,
    "High":0.0,
    "Low":0.0,
    "Close":0.0,
    "Change":0.0,
    "Trades":73.0,
    "Volume":78502.0,
    "Value":593809.45,
    "Trade_Date":"22 Jun 26",
    "Pct_Change":0.0,
    "Fetched_At":"2026-06-22 12:57:23"
  },
  {
    "Company":"ACCESSCORP",
    "Prev_Close":22.8,
    "Opening_Price":22.8,
    "High":23.0,
    "Low":22.0,
    "Close":22.8,
    "Change":0.0,
    "Trades":2407.0,
    "Volume":26082113.0,
    "Value":587972660.6000000238,
    "Trade_Date":"22 Jun 26",
    "Pct_Change":0.0,
    "Fetched_At":"2026-06-22 12:57:23"
  },
  {
    "Company":"AFRINSURE [MRF]",
    "Prev_Close":0.2,
    "Opening_Price":0.2,
    "High":0.0,
    "Low":0.0,
    "Close":0.0,
    "Change":0.0,
    "Trades":0.0,
    "Volume":0.0,
    "Value":0.0,
    "Trade_Date":"22 Jun 26",
    "Pct_Change":0.0,
    "Fetched_At":"2026-06-22 12:57:23"
  },
  {
    "Company":"AFRIPRUD",
    "Prev_Close":12.0,
    "Opening_Price":12.0,
    "High":0.0,
    "Low":0.0,
    "Close":0.0,
    "Change":0.0,
    "Trades":197.0,
    "Volume":917421.0,
    "Value":11023093.4499999993,
    "Trade_Date":"22 Jun 26",
    "Pct_Change":0.0,
    "Fetched_At":"2026-06-22 12:57:23"
  },
  {
    "Company":"AFROMEDIA [MRF]",
    "Prev_Close":0.24,
    "Opening_Price":0.24,
    "High":0.0,
    "Low":0.0,
    "Close":0.0,
    "Change":0.0,
    "Trades":0.0,
    "Volume":0.0,
    "Value":0.0,
    "Trade_Date":"22 Jun 26",
    "Pct_Change":0.0,
    "Fetched_At":"2026-06-22 12:57:23"
  },
  {
    "Company":"AIICO",
    "Prev_Close":4.0,
    "Opening_Price":4.0,
    "High":4.33,
    "Low":4.1,
    "Close":4.3,
    "Change":0.3,
    "Trades":527.0,
    "Volume":3023671.0,
    "Value":12704615.5600000005,
    "Trade_Date":"22 Jun 26",
    "Pct_Change":7.5,
    "Fetched_At":"2026-06-22 12:57:23"
  },
  {
    "Company":"AIRTELAFRI",
    "Prev_Close":3962.6,
    "Opening_Price":3962.6,
    "High":0.0,
    "Low":0.0,
    "Close":0.0,
    "Change":0.0,
    "Trades":0.0,
    "Volume":0.0,
    "Value":0.0,
    "Trade_Date":"22 Jun 26",
    "Pct_Change":0.0,
    "Fetched_At":"2026-06-22 12:57:23"
  },
  {
    "Company":"ALEX [BMF]",
    "Prev_Close":9.9,
    "Opening_Price":9.9,
    "High":0.0,
    "Low":0.0,
    "Close":0.0,
    "Change":0.0,
    "Trades":34.0,
    "Volume":244173.0,
    "Value":2205117.0,
    "Trade_Date":"22 Jun 26",
    "Pct_Change":0.0,
    "Fetched_At":"2026-06-22 12:57:23"
  },
  {
    "Company":"ARADEL [MRF]",
    "Prev_Close":1750.0,
    "Opening_Price":1750.0,
    "High":0.0,
    "Low":0.0,
    "Close":0.0,
    "Change":0.0,
    "Trades":2249.0,
    "Volume":1051174.0,
    "Value":1727013184.7999999523,
    "Trade_Date":"22 Jun 26",
    "Pct_Change":0.0,
    "Fetched_At":"2026-06-22 12:57:23"
  },
  {
    "Company":"AUSTINLAZ [RST]",
    "Prev_Close":3.9,
    "Opening_Price":3.9,
    "High":3.52,
    "Low":3.52,
    "Close":3.52,
    "Change":-0.38,
    "Trades":79.0,
    "Volume":371413.0,
    "Value":1346571.8500000001,
    "Trade_Date":"22 Jun 26",
    "Pct_Change":-9.74,
    "Fetched_At":"2026-06-22 12:57:23"
  },
  {
    "Company":"AVAIF",
    "Prev_Close":1000000.0,
    "Opening_Price":1000000.0,
    "High":0.0,
    "Low":0.0,
    "Close":0.0,
    "Change":0.0,
    "Trades":0.0,
    "Volume":0.0,
    "Value":0.0,
    "Trade_Date":"22 Jun 26",
    "Pct_Change":0.0,
    "Fetched_At":"2026-06-22 12:57:23"
  },
  {
    "Company":"BAPLC",
    "Prev_Close":6.25,
    "Opening_Price":6.25,
    "High":0.0,
    "Low":0.0,
    "Close":0.0,
    "Change":0.0,
    "Trades":0.0,
    "Volume":0.0,
    "Value":0.0,
    "Trade_Date":"22 Jun 26",
    "Pct_Change":0.0,
    "Fetched_At":"2026-06-22 12:57:23"
  },
  {
    "Company":"BERGER",
    "Prev_Close":147.6,
    "Opening_Price":147.6,
    "High":0.0,
    "Low":0.0,
    "Close":0.0,
    "Change":0.0,
    "Trades":79.0,
    "Volume":8729.0,
    "Value":1159647.6499999999,
    "Trade_Date":"22 Jun 26",
    "Pct_Change":0.0,
    "Fetched_At":"2026-06-22 12:57:23"
  },
  {
    "Company":"BETAGLAS",
    "Prev_Close":562.8,
    "Opening_Price":562.8,
    "High":0.0,
    "Low":0.0,
    "Close":0.0,
    "Change":0.0,
    "Trades":269.0,
    "Volume":36356.0,
    "Value":18645883.8000000007,
    "Trade_Date":"22 Jun 26",
    "Pct_Change":0.0,
    "Fetched_At":"2026-06-22 12:57:23"
  },
  {
    "Company":"BUACEMENT",
    "Prev_Close":378.0,
    "Opening_Price":378.0,
    "High":0.0,
    "Low":0.0,
    "Close":0.0,
    "Change":0.0,
    "Trades":760.0,
    "Volume":173792.0,
    "Value":59124038.3999999985,
    "Trade_Date":"22 Jun 26",
    "Pct_Change":0.0,
    "Fetched_At":"2026-06-22 12:57:23"
  },
  {
    "Company":"BUAFOODS",
    "Prev_Close":939.0,
    "Opening_Price":939.0,
    "High":0.0,
    "Low":0.0,
    "Close":0.0,
    "Change":0.0,
    "Trades":446.0,
    "Volume":28575.0,
    "Value":24148732.5,
    "Trade_Date":"22 Jun 26",
    "Pct_Change":0.0,
    "Fetched_At":"2026-06-22 12:57:23"
  },
  {
    "Company":"CADBURY",
    "Prev_Close":62.1,
    "Opening_Price":62.1,
    "High":0.0,
    "Low":0.0,
    "Close":0.0,
    "Change":0.0,
    "Trades":302.0,
    "Volume":365724.0,
    "Value":21741552.0500000007,
    "Trade_Date":"22 Jun 26",
    "Pct_Change":0.0,
    "Fetched_At":"2026-06-22 12:57:23"
  },
  {
    "Company":"CAP",
    "Prev_Close":175.1,
    "Opening_Price":175.1,
    "High":0.0,
    "Low":0.0,
    "Close":0.0,
    "Change":0.0,
    "Trades":28.0,
    "Volume":14377.0,
    "Value":2265822.7999999998,
    "Trade_Date":"22 Jun 26",
    "Pct_Change":0.0,
    "Fetched_At":"2026-06-22 12:57:23"
  },
  {
    "Company":"CAVERTON [MRF]",
    "Prev_Close":5.7,
    "Opening_Price":5.7,
    "High":0.0,
    "Low":0.0,
    "Close":0.0,
    "Change":0.0,
    "Trades":91.0,
    "Volume":281931.0,
    "Value":1582439.3500000001,
    "Trade_Date":"22 Jun 26",
    "Pct_Change":0.0,
    "Fetched_At":"2026-06-22 12:57:23"
  },
  {
    "Company":"CHAMPION",
    "Prev_Close":13.2,
    "Opening_Price":13.2,
    "High":13.95,
    "Low":13.05,
    "Close":13.2,
    "Change":0.0,
    "Trades":126.0,
    "Volume":2762204.0,
    "Value":36575780.950000003,
    "Trade_Date":"22 Jun 26",
    "Pct_Change":0.0,
    "Fetched_At":"2026-06-22 12:57:23"
  },
  {
    "Company":"CHAMS",
    "Prev_Close":4.01,
    "Opening_Price":4.01,
    "High":4.03,
    "Low":4.0,
    "Close":4.03,
    "Change":0.02,
    "Trades":632.0,
    "Volume":9308337.0,
    "Value":37353638.8200000003,
    "Trade_Date":"22 Jun 26",
    "Pct_Change":0.5,
    "Fetched_At":"2026-06-22 12:57:23"
  },
  {
    "Company":"CHELLARAM",
    "Prev_Close":13.2,
    "Opening_Price":13.2,
    "High":0.0,
    "Low":0.0,
    "Close":0.0,
    "Change":0.0,
    "Trades":11.0,
    "Volume":4372.0,
    "Value":54954.8,
    "Trade_Date":"22 Jun 26",
    "Pct_Change":0.0,
    "Fetched_At":"2026-06-22 12:57:23"
  },
  {
    "Company":"CILEASING",
    "Prev_Close":6.0,
    "Opening_Price":6.0,
    "High":0.0,
    "Low":0.0,
    "Close":0.0,
    "Change":0.0,
    "Trades":52.0,
    "Volume":102519.0,
    "Value":637681.6,
    "Trade_Date":"22 Jun 26",
    "Pct_Change":0.0,
    "Fetched_At":"2026-06-22 12:57:23"
  },
  {
    "Company":"CNIF",
    "Prev_Close":110.0,
    "Opening_Price":110.0,
    "High":0.0,
    "Low":0.0,
    "Close":0.0,
    "Change":0.0,
    "Trades":11.0,
    "Volume":1885.0,
    "Value":206422.2,
    "Trade_Date":"22 Jun 26",
    "Pct_Change":0.0,
    "Fetched_At":"2026-06-22 12:57:23"
  },
  {
    "Company":"CONHALLPLC",
    "Prev_Close":7.14,
    "Opening_Price":7.14,
    "High":6.85,
    "Low":6.82,
    "Close":6.82,
    "Change":-0.32,
    "Trades":118.0,
    "Volume":1419590.0,
    "Value":9823455.2200000007,
    "Trade_Date":"22 Jun 26",
    "Pct_Change":-4.48,
    "Fetched_At":"2026-06-22 12:57:23"
  },
  {
    "Company":"CONOIL",
    "Prev_Close":210.0,
    "Opening_Price":210.0,
    "High":0.0,
    "Low":0.0,
    "Close":0.0,
    "Change":0.0,
    "Trades":182.0,
    "Volume":22001.0,
    "Value":4342679.2999999998,
    "Trade_Date":"22 Jun 26",
    "Pct_Change":0.0,
    "Fetched_At":"2026-06-22 12:57:23"
  },
  {
    "Company":"CORNERST",
    "Prev_Close":6.05,
    "Opening_Price":6.05,
    "High":6.45,
    "Low":6.1,
    "Close":6.45,
    "Change":0.4,
    "Trades":157.0,
    "Volume":2298679.0,
    "Value":14223368.5,
    "Trade_Date":"22 Jun 26",
    "Pct_Change":6.61,
    "Fetched_At":"2026-06-22 12:57:23"
  },
  {
    "Company":"CUSTODIAN",
    "Prev_Close":81.25,
    "Opening_Price":81.25,
    "High":0.0,
    "Low":0.0,
    "Close":0.0,
    "Change":0.0,
    "Trades":200.0,
    "Volume":203352.0,
    "Value":15110117.25,
    "Trade_Date":"22 Jun 26",
    "Pct_Change":0.0,
    "Fetched_At":"2026-06-22 12:57:23"
  },
  {
    "Company":"CUTIX",
    "Prev_Close":2.98,
    "Opening_Price":2.98,
    "High":3.0,
    "Low":2.98,
    "Close":2.98,
    "Change":0.0,
    "Trades":164.0,
    "Volume":2662152.0,
    "Value":7950921.4199999999,
    "Trade_Date":"22 Jun 26",
    "Pct_Change":0.0,
    "Fetched_At":"2026-06-22 12:57:23"
  },
  {
    "Company":"CWG",
    "Prev_Close":20.65,
    "Opening_Price":20.65,
    "High":0.0,
    "Low":0.0,
    "Close":0.0,
    "Change":0.0,
    "Trades":219.0,
    "Volume":509698.0,
    "Value":10332883.9000000004,
    "Trade_Date":"22 Jun 26",
    "Pct_Change":0.0,
    "Fetched_At":"2026-06-22 12:57:23"
  },
  {
    "Company":"DAARCOMM",
    "Prev_Close":1.81,
    "Opening_Price":1.81,
    "High":0.0,
    "Low":0.0,
    "Close":0.0,
    "Change":0.0,
    "Trades":181.0,
    "Volume":1204107.0,
    "Value":2194165.5600000001,
    "Trade_Date":"22 Jun 26",
    "Pct_Change":0.0,
    "Fetched_At":"2026-06-22 12:57:23"
  },
  {
    "Company":"DANGCEM",
    "Prev_Close":1070.0,
    "Opening_Price":1070.0,
    "High":0.0,
    "Low":0.0,
    "Close":0.0,
    "Change":0.0,
    "Trades":2195.0,
    "Volume":211363.0,
    "Value":206954434.6999999881,
    "Trade_Date":"22 Jun 26",
    "Pct_Change":0.0,
    "Fetched_At":"2026-06-22 12:57:23"
  },
  {
    "Company":"DANGSUGAR",
    "Prev_Close":74.0,
    "Opening_Price":74.0,
    "High":74.0,
    "Low":73.0,
    "Close":73.9,
    "Change":-0.1,
    "Trades":2113.0,
    "Volume":5617060.0,
    "Value":414465320.1999999881,
    "Trade_Date":"22 Jun 26",
    "Pct_Change":-0.14,
    "Fetched_At":"2026-06-22 12:57:23"
  },
  {
    "Company":"DEAPCAP [DWL]",
    "Prev_Close":4.89,
    "Opening_Price":4.89,
    "High":4.77,
    "Low":4.75,
    "Close":4.77,
    "Change":-0.12,
    "Trades":215.0,
    "Volume":1737784.0,
    "Value":8317705.5599999996,
    "Trade_Date":"22 Jun 26",
    "Pct_Change":-2.45,
    "Fetched_At":"2026-06-22 12:57:23"
  },
  {
    "Company":"EKOCORP [DIP]",
    "Prev_Close":5.8,
    "Opening_Price":5.8,
    "High":0.0,
    "Low":0.0,
    "Close":0.0,
    "Change":0.0,
    "Trades":0.0,
    "Volume":0.0,
    "Value":0.0,
    "Trade_Date":"22 Jun 26",
    "Pct_Change":0.0,
    "Fetched_At":"2026-06-22 12:57:23"
  },
  {
    "Company":"ELLAHLAKES",
    "Prev_Close":8.75,
    "Opening_Price":8.75,
    "High":8.6,
    "Low":8.6,
    "Close":8.6,
    "Change":-0.15,
    "Trades":283.0,
    "Volume":1437967.0,
    "Value":12552505.5500000007,
    "Trade_Date":"22 Jun 26",
    "Pct_Change":-1.71,
    "Fetched_At":"2026-06-22 12:57:23"
  },
  {
    "Company":"ENAMELWA",
    "Prev_Close":40.7,
    "Opening_Price":40.7,
    "High":0.0,
    "Low":0.0,
    "Close":0.0,
    "Change":0.0,
    "Trades":0.0,
    "Volume":0.0,
    "Value":0.0,
    "Trade_Date":"22 Jun 26",
    "Pct_Change":0.0,
    "Fetched_At":"2026-06-22 12:57:23"
  },
  {
    "Company":"ETERNA",
    "Prev_Close":30.8,
    "Opening_Price":30.8,
    "High":27.75,
    "Low":27.75,
    "Close":27.75,
    "Change":-3.05,
    "Trades":170.0,
    "Volume":1100272.0,
    "Value":31422682.75,
    "Trade_Date":"22 Jun 26",
    "Pct_Change":-9.9,
    "Fetched_At":"2026-06-22 12:57:23"
  },
  {
    "Company":"ETI",
    "Prev_Close":95.2,
    "Opening_Price":95.2,
    "High":0.0,
    "Low":0.0,
    "Close":0.0,
    "Change":0.0,
    "Trades":42.0,
    "Volume":19105.0,
    "Value":1637298.5,
    "Trade_Date":"22 Jun 26",
    "Pct_Change":0.0,
    "Fetched_At":"2026-06-22 12:57:23"
  },
  {
    "Company":"ETRANZACT",
    "Prev_Close":16.35,
    "Opening_Price":16.35,
    "High":0.0,
    "Low":0.0,
    "Close":0.0,
    "Change":0.0,
    "Trades":116.0,
    "Volume":154288.0,
    "Value":2425612.8999999999,
    "Trade_Date":"22 Jun 26",
    "Pct_Change":0.0,
    "Fetched_At":"2026-06-22 12:57:23"
  },
  {
    "Company":"EUNISELL",
    "Prev_Close":210.0,
    "Opening_Price":210.0,
    "High":0.0,
    "Low":0.0,
    "Close":0.0,
    "Change":0.0,
    "Trades":23.0,
    "Volume":3369.0,
    "Value":636741.0,
    "Trade_Date":"22 Jun 26",
    "Pct_Change":0.0,
    "Fetched_At":"2026-06-22 12:57:23"
  },
  {
    "Company":"FCMB",
    "Prev_Close":10.9,
    "Opening_Price":10.9,
    "High":10.7,
    "Low":10.6,
    "Close":10.6,
    "Change":-0.3,
    "Trades":623.0,
    "Volume":4513445.0,
    "Value":48389955.0,
    "Trade_Date":"22 Jun 26",
    "Pct_Change":-2.75,
    "Fetched_At":"2026-06-22 12:57:23"
  },
  {
    "Company":"FIDELITYBK",
    "Prev_Close":18.0,
    "Opening_Price":18.0,
    "High":19.55,
    "Low":18.0,
    "Close":18.0,
    "Change":0.0,
    "Trades":742.0,
    "Volume":28322356.0,
    "Value":526974916.75,
    "Trade_Date":"22 Jun 26",
    "Pct_Change":0.0,
    "Fetched_At":"2026-06-22 12:57:23"
  },
  {
    "Company":"FIDSON",
    "Prev_Close":101.2,
    "Opening_Price":101.2,
    "High":0.0,
    "Low":0.0,
    "Close":0.0,
    "Change":0.0,
    "Trades":918.0,
    "Volume":444718.0,
    "Value":42456302.450000003,
    "Trade_Date":"22 Jun 26",
    "Pct_Change":0.0,
    "Fetched_At":"2026-06-22 12:57:23"
  },
  {
    "Company":"FIRSTHOLDCO",
    "Prev_Close":55.0,
    "Opening_Price":55.0,
    "High":60.5,
    "Low":58.0,
    "Close":60.5,
    "Change":5.5,
    "Trades":1094.0,
    "Volume":9410781.0,
    "Value":562468617.1499999762,
    "Trade_Date":"22 Jun 26",
    "Pct_Change":10.0,
    "Fetched_At":"2026-06-22 12:57:23"
  },
  {
    "Company":"FTGINSURE [DWL]",
    "Prev_Close":0.99,
    "Opening_Price":0.99,
    "High":0.0,
    "Low":0.0,
    "Close":0.0,
    "Change":0.0,
    "Trades":0.0,
    "Volume":0.0,
    "Value":0.0,
    "Trade_Date":"22 Jun 26",
    "Pct_Change":0.0,
    "Fetched_At":"2026-06-22 12:57:23"
  },
  {
    "Company":"FTNCOCOA [RST]",
    "Prev_Close":7.92,
    "Opening_Price":7.92,
    "High":7.9,
    "Low":7.45,
    "Close":7.45,
    "Change":-0.47,
    "Trades":272.0,
    "Volume":1300917.0,
    "Value":10002132.0,
    "Trade_Date":"22 Jun 26",
    "Pct_Change":-5.93,
    "Fetched_At":"2026-06-22 12:57:23"
  },
  {
    "Company":"GEREGU",
    "Prev_Close":1019.3,
    "Opening_Price":1019.3,
    "High":0.0,
    "Low":0.0,
    "Close":0.0,
    "Change":0.0,
    "Trades":49.0,
    "Volume":2894.0,
    "Value":2654955.6000000001,
    "Trade_Date":"22 Jun 26",
    "Pct_Change":0.0,
    "Fetched_At":"2026-06-22 12:57:23"
  },
  {
    "Company":"GOLDBREW [BMF]",
    "Prev_Close":7.1,
    "Opening_Price":7.1,
    "High":0.0,
    "Low":0.0,
    "Close":0.0,
    "Change":0.0,
    "Trades":0.0,
    "Volume":0.0,
    "Value":0.0,
    "Trade_Date":"22 Jun 26",
    "Pct_Change":0.0,
    "Fetched_At":"2026-06-22 12:57:23"
  },
  {
    "Company":"GTCO",
    "Prev_Close":115.55,
    "Opening_Price":115.55,
    "High":127.1,
    "Low":127.05,
    "Close":127.1,
    "Change":11.55,
    "Trades":3391.0,
    "Volume":13792675.0,
    "Value":1751269973.6500000954,
    "Trade_Date":"22 Jun 26",
    "Pct_Change":10.0,
    "Fetched_At":"2026-06-22 12:57:23"
  },
  {
    "Company":"GUINEAINS",
    "Prev_Close":1.0,
    "Opening_Price":1.0,
    "High":1.02,
    "Low":1.0,
    "Close":1.0,
    "Change":0.0,
    "Trades":71.0,
    "Volume":1953927.0,
    "Value":1982534.9099999999,
    "Trade_Date":"22 Jun 26",
    "Pct_Change":0.0,
    "Fetched_At":"2026-06-22 12:57:23"
  },
  {
    "Company":"GUINNESS",
    "Prev_Close":365.5,
    "Opening_Price":365.5,
    "High":0.0,
    "Low":0.0,
    "Close":0.0,
    "Change":0.0,
    "Trades":140.0,
    "Volume":37036.0,
    "Value":12185159.0,
    "Trade_Date":"22 Jun 26",
    "Pct_Change":0.0,
    "Fetched_At":"2026-06-22 12:57:23"
  },
  {
    "Company":"HMCALL",
    "Prev_Close":3.92,
    "Opening_Price":3.92,
    "High":0.0,
    "Low":0.0,
    "Close":0.0,
    "Change":0.0,
    "Trades":29.0,
    "Volume":32175.0,
    "Value":116902.17,
    "Trade_Date":"22 Jun 26",
    "Pct_Change":0.0,
    "Fetched_At":"2026-06-22 12:57:23"
  },
  {
    "Company":"HONYFLOUR",
    "Prev_Close":16.7,
    "Opening_Price":16.7,
    "High":0.0,
    "Low":0.0,
    "Close":0.0,
    "Change":0.0,
    "Trades":279.0,
    "Volume":394371.0,
    "Value":6881199.2000000002,
    "Trade_Date":"22 Jun 26",
    "Pct_Change":0.0,
    "Fetched_At":"2026-06-22 12:57:23"
  },
  {
    "Company":"IKEJAHOTEL",
    "Prev_Close":44.6,
    "Opening_Price":44.6,
    "High":0.0,
    "Low":0.0,
    "Close":0.0,
    "Change":0.0,
    "Trades":69.0,
    "Volume":40743.0,
    "Value":1725533.55,
    "Trade_Date":"22 Jun 26",
    "Pct_Change":0.0,
    "Fetched_At":"2026-06-22 12:57:23"
  },
  {
    "Company":"IMG",
    "Prev_Close":34.1,
    "Opening_Price":34.1,
    "High":0.0,
    "Low":0.0,
    "Close":0.0,
    "Change":0.0,
    "Trades":14.0,
    "Volume":70044.0,
    "Value":2150400.7999999998,
    "Trade_Date":"22 Jun 26",
    "Pct_Change":0.0,
    "Fetched_At":"2026-06-22 12:57:23"
  },
  {
    "Company":"INFINITY [BLS]",
    "Prev_Close":11.25,
    "Opening_Price":11.25,
    "High":0.0,
    "Low":0.0,
    "Close":0.0,
    "Change":0.0,
    "Trades":12.0,
    "Volume":30593.0,
    "Value":310518.95,
    "Trade_Date":"22 Jun 26",
    "Pct_Change":0.0,
    "Fetched_At":"2026-06-22 12:57:23"
  },
  {
    "Company":"INTBREW",
    "Prev_Close":10.8,
    "Opening_Price":10.8,
    "High":0.0,
    "Low":0.0,
    "Close":0.0,
    "Change":0.0,
    "Trades":132.0,
    "Volume":516746.0,
    "Value":5671797.9500000002,
    "Trade_Date":"22 Jun 26",
    "Pct_Change":0.0,
    "Fetched_At":"2026-06-22 12:57:23"
  },
  {
    "Company":"INTENEGINS",
    "Prev_Close":5.06,
    "Opening_Price":5.06,
    "High":5.56,
    "Low":5.43,
    "Close":5.56,
    "Change":0.5,
    "Trades":410.0,
    "Volume":5208776.0,
    "Value":28459408.5100000016,
    "Trade_Date":"22 Jun 26",
    "Pct_Change":9.88,
    "Fetched_At":"2026-06-22 12:57:23"
  },
  {
    "Company":"JAIZBANK",
    "Prev_Close":9.0,
    "Opening_Price":9.0,
    "High":9.1,
    "Low":8.55,
    "Close":8.55,
    "Change":-0.45,
    "Trades":1367.0,
    "Volume":4679382.0,
    "Value":41152341.3500000015,
    "Trade_Date":"22 Jun 26",
    "Pct_Change":-5.0,
    "Fetched_At":"2026-06-22 12:57:23"
  },
  {
    "Company":"JAPAULGOLD [MRF]",
    "Prev_Close":3.25,
    "Opening_Price":3.25,
    "High":3.2,
    "Low":3.16,
    "Close":3.2,
    "Change":-0.05,
    "Trades":384.0,
    "Volume":3883830.0,
    "Value":12418449.8499999996,
    "Trade_Date":"22 Jun 26",
    "Pct_Change":-1.54,
    "Fetched_At":"2026-06-22 12:57:23"
  },
  {
    "Company":"JBERGER",
    "Prev_Close":310.8,
    "Opening_Price":310.8,
    "High":0.0,
    "Low":0.0,
    "Close":0.0,
    "Change":0.0,
    "Trades":69.0,
    "Volume":6422.0,
    "Value":1796875.6000000001,
    "Trade_Date":"22 Jun 26",
    "Pct_Change":0.0,
    "Fetched_At":"2026-06-22 12:57:23"
  },
  {
    "Company":"JOHNHOLT",
    "Prev_Close":11.2,
    "Opening_Price":11.2,
    "High":0.0,
    "Low":0.0,
    "Close":0.0,
    "Change":0.0,
    "Trades":70.0,
    "Volume":227868.0,
    "Value":2549527.0499999998,
    "Trade_Date":"22 Jun 26",
    "Pct_Change":0.0,
    "Fetched_At":"2026-06-22 12:57:23"
  },
  {
    "Company":"JULI",
    "Prev_Close":7.25,
    "Opening_Price":7.25,
    "High":0.0,
    "Low":0.0,
    "Close":0.0,
    "Change":0.0,
    "Trades":2.0,
    "Volume":2200.0,
    "Value":14410.0,
    "Trade_Date":"22 Jun 26",
    "Pct_Change":0.0,
    "Fetched_At":"2026-06-22 12:57:23"
  },
  {
    "Company":"LASACO",
    "Prev_Close":1.9,
    "Opening_Price":1.9,
    "High":2.05,
    "Low":1.92,
    "Close":1.99,
    "Change":0.09,
    "Trades":85.0,
    "Volume":1389630.0,
    "Value":2725783.98,
    "Trade_Date":"22 Jun 26",
    "Pct_Change":4.74,
    "Fetched_At":"2026-06-22 12:57:23"
  },
  {
    "Company":"LEARNAFRCA",
    "Prev_Close":11.0,
    "Opening_Price":11.0,
    "High":0.0,
    "Low":0.0,
    "Close":0.0,
    "Change":0.0,
    "Trades":71.0,
    "Volume":467844.0,
    "Value":5094674.0999999996,
    "Trade_Date":"22 Jun 26",
    "Pct_Change":0.0,
    "Fetched_At":"2026-06-22 12:57:23"
  },
  {
    "Company":"LEGENDINT [MRF]",
    "Prev_Close":5.5,
    "Opening_Price":5.5,
    "High":6.0,
    "Low":5.65,
    "Close":6.0,
    "Change":0.5,
    "Trades":23.0,
    "Volume":466044.0,
    "Value":2705421.3999999999,
    "Trade_Date":"22 Jun 26",
    "Pct_Change":9.09,
    "Fetched_At":"2026-06-22 12:57:23"
  },
  {
    "Company":"LINKASSURE",
    "Prev_Close":1.64,
    "Opening_Price":1.64,
    "High":1.6,
    "Low":1.56,
    "Close":1.57,
    "Change":-0.07,
    "Trades":76.0,
    "Volume":3207072.0,
    "Value":5066056.25,
    "Trade_Date":"22 Jun 26",
    "Pct_Change":-4.27,
    "Fetched_At":"2026-06-22 12:57:23"
  },
  {
    "Company":"LIVESTOCK",
    "Prev_Close":8.65,
    "Opening_Price":8.65,
    "High":0.0,
    "Low":0.0,
    "Close":0.0,
    "Change":0.0,
    "Trades":176.0,
    "Volume":335872.0,
    "Value":2816862.8999999999,
    "Trade_Date":"22 Jun 26",
    "Pct_Change":0.0,
    "Fetched_At":"2026-06-22 12:57:23"
  },
  {
    "Company":"LIVINGTRUST [MRF]",
    "Prev_Close":4.0,
    "Opening_Price":4.0,
    "High":0.0,
    "Low":0.0,
    "Close":0.0,
    "Change":0.0,
    "Trades":39.0,
    "Volume":35485.0,
    "Value":140015.59,
    "Trade_Date":"22 Jun 26",
    "Pct_Change":0.0,
    "Fetched_At":"2026-06-22 12:57:23"
  },
  {
    "Company":"MANSARD",
    "Prev_Close":12.85,
    "Opening_Price":12.85,
    "High":0.0,
    "Low":0.0,
    "Close":0.0,
    "Change":0.0,
    "Trades":116.0,
    "Volume":549302.0,
    "Value":6859917.5999999996,
    "Trade_Date":"22 Jun 26",
    "Pct_Change":0.0,
    "Fetched_At":"2026-06-22 12:57:23"
  },
  {
    "Company":"MAYBAKER",
    "Prev_Close":40.0,
    "Opening_Price":40.0,
    "High":0.0,
    "Low":0.0,
    "Close":0.0,
    "Change":0.0,
    "Trades":353.0,
    "Volume":356363.0,
    "Value":13178290.8499999996,
    "Trade_Date":"22 Jun 26",
    "Pct_Change":0.0,
    "Fetched_At":"2026-06-22 12:57:23"
  },
  {
    "Company":"MBENEFIT",
    "Prev_Close":3.7,
    "Opening_Price":3.7,
    "High":3.7,
    "Low":3.65,
    "Close":3.65,
    "Change":-0.05,
    "Trades":224.0,
    "Volume":3203659.0,
    "Value":11746712.9800000004,
    "Trade_Date":"22 Jun 26",
    "Pct_Change":-1.35,
    "Fetched_At":"2026-06-22 12:57:23"
  },
  {
    "Company":"MCNICHOLS",
    "Prev_Close":6.8,
    "Opening_Price":6.8,
    "High":7.45,
    "Low":7.45,
    "Close":7.45,
    "Change":0.65,
    "Trades":114.0,
    "Volume":1777761.0,
    "Value":13130653.3000000007,
    "Trade_Date":"22 Jun 26",
    "Pct_Change":9.56,
    "Fetched_At":"2026-06-22 12:57:23"
  },
  {
    "Company":"MECURE",
    "Prev_Close":94.9,
    "Opening_Price":94.9,
    "High":0.0,
    "Low":0.0,
    "Close":0.0,
    "Change":0.0,
    "Trades":63.0,
    "Volume":52671.0,
    "Value":4500736.9500000002,
    "Trade_Date":"22 Jun 26",
    "Pct_Change":0.0,
    "Fetched_At":"2026-06-22 12:57:23"
  },
  {
    "Company":"MEYER",
    "Prev_Close":20.6,
    "Opening_Price":20.6,
    "High":0.0,
    "Low":0.0,
    "Close":0.0,
    "Change":0.0,
    "Trades":22.0,
    "Volume":4571.0,
    "Value":87611.1,
    "Trade_Date":"22 Jun 26",
    "Pct_Change":0.0,
    "Fetched_At":"2026-06-22 12:57:23"
  },
  {
    "Company":"MOFIREIF",
    "Prev_Close":100.0,
    "Opening_Price":100.0,
    "High":0.0,
    "Low":0.0,
    "Close":0.0,
    "Change":0.0,
    "Trades":0.0,
    "Volume":0.0,
    "Value":0.0,
    "Trade_Date":"22 Jun 26",
    "Pct_Change":0.0,
    "Fetched_At":"2026-06-22 12:57:23"
  },
  {
    "Company":"MORISON",
    "Prev_Close":10.6,
    "Opening_Price":10.6,
    "High":0.0,
    "Low":0.0,
    "Close":0.0,
    "Change":0.0,
    "Trades":4.0,
    "Volume":2752.0,
    "Value":26281.6,
    "Trade_Date":"22 Jun 26",
    "Pct_Change":0.0,
    "Fetched_At":"2026-06-22 12:57:23"
  },
  {
    "Company":"MTNN",
    "Prev_Close":800.0,
    "Opening_Price":800.0,
    "High":830.0,
    "Low":797.0,
    "Close":830.0,
    "Change":30.0,
    "Trades":4977.0,
    "Volume":7297680.0,
    "Value":5977306777.3999996185,
    "Trade_Date":"22 Jun 26",
    "Pct_Change":3.75,
    "Fetched_At":"2026-06-22 12:57:23"
  },
  {
    "Company":"MULTITREX [DWL]",
    "Prev_Close":0.36,
    "Opening_Price":0.36,
    "High":0.0,
    "Low":0.0,
    "Close":0.0,
    "Change":0.0,
    "Trades":0.0,
    "Volume":0.0,
    "Value":0.0,
    "Trade_Date":"22 Jun 26",
    "Pct_Change":0.0,
    "Fetched_At":"2026-06-22 12:57:23"
  },
  {
    "Company":"MULTIVERSE",
    "Prev_Close":25.5,
    "Opening_Price":25.5,
    "High":0.0,
    "Low":0.0,
    "Close":0.0,
    "Change":0.0,
    "Trades":10.0,
    "Volume":7371.0,
    "Value":169174.45,
    "Trade_Date":"22 Jun 26",
    "Pct_Change":0.0,
    "Fetched_At":"2026-06-22 12:57:23"
  },
  {
    "Company":"NAHCO",
    "Prev_Close":148.5,
    "Opening_Price":148.5,
    "High":0.0,
    "Low":0.0,
    "Close":0.0,
    "Change":0.0,
    "Trades":721.0,
    "Volume":826887.0,
    "Value":119360761.650000006,
    "Trade_Date":"22 Jun 26",
    "Pct_Change":0.0,
    "Fetched_At":"2026-06-22 12:57:23"
  },
  {
    "Company":"NASCON",
    "Prev_Close":219.5,
    "Opening_Price":219.5,
    "High":0.0,
    "Low":0.0,
    "Close":0.0,
    "Change":0.0,
    "Trades":219.0,
    "Volume":147485.0,
    "Value":29214379.0,
    "Trade_Date":"22 Jun 26",
    "Pct_Change":0.0,
    "Fetched_At":"2026-06-22 12:57:23"
  },
  {
    "Company":"NB",
    "Prev_Close":79.0,
    "Opening_Price":79.0,
    "High":76.0,
    "Low":76.0,
    "Close":76.0,
    "Change":-3.0,
    "Trades":295.0,
    "Volume":9392499.0,
    "Value":713858953.2000000477,
    "Trade_Date":"22 Jun 26",
    "Pct_Change":-3.8,
    "Fetched_At":"2026-06-22 12:57:23"
  },
  {
    "Company":"NCR",
    "Prev_Close":161.2,
    "Opening_Price":161.2,
    "High":0.0,
    "Low":0.0,
    "Close":0.0,
    "Change":0.0,
    "Trades":16.0,
    "Volume":5200.0,
    "Value":754520.0,
    "Trade_Date":"22 Jun 26",
    "Pct_Change":0.0,
    "Fetched_At":"2026-06-22 12:57:23"
  },
  {
    "Company":"NEIMETH",
    "Prev_Close":8.95,
    "Opening_Price":8.95,
    "High":8.5,
    "Low":8.5,
    "Close":8.5,
    "Change":-0.45,
    "Trades":216.0,
    "Volume":965732.0,
    "Value":8347927.1500000004,
    "Trade_Date":"22 Jun 26",
    "Pct_Change":-5.03,
    "Fetched_At":"2026-06-22 12:57:23"
  },
  {
    "Company":"NEM",
    "Prev_Close":29.0,
    "Opening_Price":29.0,
    "High":0.0,
    "Low":0.0,
    "Close":0.0,
    "Change":0.0,
    "Trades":81.0,
    "Volume":338948.0,
    "Value":9976749.75,
    "Trade_Date":"22 Jun 26",
    "Pct_Change":0.0,
    "Fetched_At":"2026-06-22 12:57:23"
  },
  {
    "Company":"NESTLE",
    "Prev_Close":3125.0,
    "Opening_Price":3125.0,
    "High":0.0,
    "Low":0.0,
    "Close":0.0,
    "Change":0.0,
    "Trades":163.0,
    "Volume":5360.0,
    "Value":15157036.5999999996,
    "Trade_Date":"22 Jun 26",
    "Pct_Change":0.0,
    "Fetched_At":"2026-06-22 12:57:23"
  },
  {
    "Company":"NGXGROUP",
    "Prev_Close":122.8,
    "Opening_Price":122.8,
    "High":0.0,
    "Low":0.0,
    "Close":0.0,
    "Change":0.0,
    "Trades":1154.0,
    "Volume":1265995.0,
    "Value":155346697.0,
    "Trade_Date":"22 Jun 26",
    "Pct_Change":0.0,
    "Fetched_At":"2026-06-22 12:57:23"
  },
  {
    "Company":"NIDF",
    "Prev_Close":129.0,
    "Opening_Price":129.0,
    "High":0.0,
    "Low":0.0,
    "Close":0.0,
    "Change":0.0,
    "Trades":115.0,
    "Volume":103915.0,
    "Value":14738786.6999999993,
    "Trade_Date":"22 Jun 26",
    "Pct_Change":0.0,
    "Fetched_At":"2026-06-22 12:57:23"
  },
  {
    "Company":"NNFM",
    "Prev_Close":79.4,
    "Opening_Price":79.4,
    "High":0.0,
    "Low":0.0,
    "Close":0.0,
    "Change":0.0,
    "Trades":13.0,
    "Volume":5819.0,
    "Value":416058.5,
    "Trade_Date":"22 Jun 26",
    "Pct_Change":0.0,
    "Fetched_At":"2026-06-22 12:57:23"
  },
  {
    "Company":"NPFMCRFBK",
    "Prev_Close":4.9,
    "Opening_Price":4.9,
    "High":5.15,
    "Low":5.15,
    "Close":5.15,
    "Change":0.25,
    "Trades":97.0,
    "Volume":736737.0,
    "Value":3802205.7000000002,
    "Trade_Date":"22 Jun 26",
    "Pct_Change":5.1,
    "Fetched_At":"2026-06-22 12:57:23"
  },
  {
    "Company":"NREIT",
    "Prev_Close":103.0,
    "Opening_Price":103.0,
    "High":0.0,
    "Low":0.0,
    "Close":0.0,
    "Change":0.0,
    "Trades":36.0,
    "Volume":31323.0,
    "Value":3035135.6000000001,
    "Trade_Date":"22 Jun 26",
    "Pct_Change":0.0,
    "Fetched_At":"2026-06-22 12:57:23"
  },
  {
    "Company":"NSLTECH",
    "Prev_Close":0.81,
    "Opening_Price":0.81,
    "High":0.85,
    "Low":0.8,
    "Close":0.85,
    "Change":0.04,
    "Trades":160.0,
    "Volume":4168743.0,
    "Value":3429815.8500000001,
    "Trade_Date":"22 Jun 26",
    "Pct_Change":4.94,
    "Fetched_At":"2026-06-22 12:57:23"
  },
  {
    "Company":"OANDO",
    "Prev_Close":46.0,
    "Opening_Price":46.0,
    "High":0.0,
    "Low":0.0,
    "Close":0.0,
    "Change":0.0,
    "Trades":524.0,
    "Volume":756680.0,
    "Value":34723584.5,
    "Trade_Date":"22 Jun 26",
    "Pct_Change":0.0,
    "Fetched_At":"2026-06-22 12:57:23"
  },
  {
    "Company":"OKOMUOIL",
    "Prev_Close":1418.0,
    "Opening_Price":1418.0,
    "High":0.0,
    "Low":0.0,
    "Close":0.0,
    "Change":0.0,
    "Trades":532.0,
    "Volume":50775.0,
    "Value":64973871.3999999985,
    "Trade_Date":"22 Jun 26",
    "Pct_Change":0.0,
    "Fetched_At":"2026-06-22 12:57:23"
  },
  {
    "Company":"OMATEK",
    "Prev_Close":1.97,
    "Opening_Price":1.97,
    "High":1.93,
    "Low":1.93,
    "Close":1.93,
    "Change":-0.04,
    "Trades":106.0,
    "Volume":876270.0,
    "Value":1630711.3700000001,
    "Trade_Date":"22 Jun 26",
    "Pct_Change":-2.03,
    "Fetched_At":"2026-06-22 12:57:23"
  },
  {
    "Company":"PHARMDEKO",
    "Prev_Close":1.83,
    "Opening_Price":1.83,
    "High":0.0,
    "Low":0.0,
    "Close":0.0,
    "Change":0.0,
    "Trades":0.0,
    "Volume":0.0,
    "Value":0.0,
    "Trade_Date":"22 Jun 26",
    "Pct_Change":0.0,
    "Fetched_At":"2026-06-22 12:57:23"
  },
  {
    "Company":"PREMPAINTS",
    "Prev_Close":33.75,
    "Opening_Price":33.75,
    "High":0.0,
    "Low":0.0,
    "Close":0.0,
    "Change":0.0,
    "Trades":13.0,
    "Volume":54322.0,
    "Value":1651508.8,
    "Trade_Date":"22 Jun 26",
    "Pct_Change":0.0,
    "Fetched_At":"2026-06-22 12:57:23"
  },
  {
    "Company":"PRESCO",
    "Prev_Close":2300.0,
    "Opening_Price":2300.0,
    "High":0.0,
    "Low":0.0,
    "Close":0.0,
    "Change":0.0,
    "Trades":221.0,
    "Volume":25190.0,
    "Value":52143300.0,
    "Trade_Date":"22 Jun 26",
    "Pct_Change":0.0,
    "Fetched_At":"2026-06-22 12:57:23"
  },
  {
    "Company":"PRESTIGE [BLS]",
    "Prev_Close":1.41,
    "Opening_Price":1.41,
    "High":1.38,
    "Low":1.38,
    "Close":1.38,
    "Change":-0.03,
    "Trades":28.0,
    "Volume":489423.0,
    "Value":678889.84,
    "Trade_Date":"22 Jun 26",
    "Pct_Change":-2.13,
    "Fetched_At":"2026-06-22 12:57:23"
  },
  {
    "Company":"PZ",
    "Prev_Close":94.95,
    "Opening_Price":94.95,
    "High":0.0,
    "Low":0.0,
    "Close":0.0,
    "Change":0.0,
    "Trades":141.0,
    "Volume":681985.0,
    "Value":58323788.0,
    "Trade_Date":"22 Jun 26",
    "Pct_Change":0.0,
    "Fetched_At":"2026-06-22 12:57:23"
  },
  {
    "Company":"REDSTAREX",
    "Prev_Close":27.6,
    "Opening_Price":27.6,
    "High":0.0,
    "Low":0.0,
    "Close":0.0,
    "Change":0.0,
    "Trades":8.0,
    "Volume":19890.0,
    "Value":494266.5,
    "Trade_Date":"22 Jun 26",
    "Pct_Change":0.0,
    "Fetched_At":"2026-06-22 12:57:23"
  },
  {
    "Company":"REGALINS",
    "Prev_Close":0.97,
    "Opening_Price":0.97,
    "High":1.02,
    "Low":0.94,
    "Close":0.94,
    "Change":-0.03,
    "Trades":85.0,
    "Volume":3750980.0,
    "Value":3644680.8799999999,
    "Trade_Date":"22 Jun 26",
    "Pct_Change":-3.09,
    "Fetched_At":"2026-06-22 12:57:23"
  },
  {
    "Company":"RONCHESS",
    "Prev_Close":81.0,
    "Opening_Price":81.0,
    "High":0.0,
    "Low":0.0,
    "Close":0.0,
    "Change":0.0,
    "Trades":0.0,
    "Volume":0.0,
    "Value":0.0,
    "Trade_Date":"22 Jun 26",
    "Pct_Change":0.0,
    "Fetched_At":"2026-06-22 12:57:23"
  },
  {
    "Company":"ROYALEX",
    "Prev_Close":1.53,
    "Opening_Price":1.53,
    "High":1.6,
    "Low":1.6,
    "Close":1.6,
    "Change":0.07,
    "Trades":82.0,
    "Volume":2552513.0,
    "Value":4080018.79,
    "Trade_Date":"22 Jun 26",
    "Pct_Change":4.58,
    "Fetched_At":"2026-06-22 12:57:23"
  },
  {
    "Company":"RTBRISCOE",
    "Prev_Close":13.1,
    "Opening_Price":13.1,
    "High":12.85,
    "Low":12.2,
    "Close":12.85,
    "Change":-0.25,
    "Trades":166.0,
    "Volume":857688.0,
    "Value":10664423.4000000004,
    "Trade_Date":"22 Jun 26",
    "Pct_Change":-1.91,
    "Fetched_At":"2026-06-22 12:57:23"
  },
  {
    "Company":"SCOA",
    "Prev_Close":33.05,
    "Opening_Price":33.05,
    "High":0.0,
    "Low":0.0,
    "Close":0.0,
    "Change":0.0,
    "Trades":15.0,
    "Volume":7197.0,
    "Value":214110.75,
    "Trade_Date":"22 Jun 26",
    "Pct_Change":0.0,
    "Fetched_At":"2026-06-22 12:57:23"
  },
  {
    "Company":"SEPLAT",
    "Prev_Close":11363.9,
    "Opening_Price":11363.9,
    "High":0.0,
    "Low":0.0,
    "Close":0.0,
    "Change":0.0,
    "Trades":318.0,
    "Volume":78042.0,
    "Value":798182363.5,
    "Trade_Date":"22 Jun 26",
    "Pct_Change":0.0,
    "Fetched_At":"2026-06-22 12:57:23"
  },
  {
    "Company":"SFSREIT",
    "Prev_Close":418.75,
    "Opening_Price":418.75,
    "High":0.0,
    "Low":0.0,
    "Close":0.0,
    "Change":0.0,
    "Trades":30.0,
    "Volume":6904.0,
    "Value":3011418.6000000001,
    "Trade_Date":"22 Jun 26",
    "Pct_Change":0.0,
    "Fetched_At":"2026-06-22 12:57:23"
  },
  {
    "Company":"SKYAVN",
    "Prev_Close":155.75,
    "Opening_Price":155.75,
    "High":0.0,
    "Low":0.0,
    "Close":0.0,
    "Change":0.0,
    "Trades":13.0,
    "Volume":4154.0,
    "Value":582390.8,
    "Trade_Date":"22 Jun 26",
    "Pct_Change":0.0,
    "Fetched_At":"2026-06-22 12:57:23"
  },
  {
    "Company":"SOVRENINS",
    "Prev_Close":2.16,
    "Opening_Price":2.16,
    "High":2.16,
    "Low":2.15,
    "Close":2.15,
    "Change":-0.01,
    "Trades":50.0,
    "Volume":624898.0,
    "Value":1352240.3799999999,
    "Trade_Date":"22 Jun 26",
    "Pct_Change":-0.46,
    "Fetched_At":"2026-06-22 12:57:23"
  },
  {
    "Company":"STACO",
    "Prev_Close":0.48,
    "Opening_Price":0.48,
    "High":0.0,
    "Low":0.0,
    "Close":0.0,
    "Change":0.0,
    "Trades":0.0,
    "Volume":0.0,
    "Value":0.0,
    "Trade_Date":"22 Jun 26",
    "Pct_Change":0.0,
    "Fetched_At":"2026-06-22 12:57:23"
  },
  {
    "Company":"STANBIC",
    "Prev_Close":163.0,
    "Opening_Price":163.0,
    "High":0.0,
    "Low":0.0,
    "Close":0.0,
    "Change":0.0,
    "Trades":369.0,
    "Volume":225808.0,
    "Value":35426973.0,
    "Trade_Date":"22 Jun 26",
    "Pct_Change":0.0,
    "Fetched_At":"2026-06-22 12:57:23"
  },
  {
    "Company":"STERLINGNG",
    "Prev_Close":7.75,
    "Opening_Price":7.75,
    "High":7.55,
    "Low":7.45,
    "Close":7.45,
    "Change":-0.3,
    "Trades":295.0,
    "Volume":7760552.0,
    "Value":58206521.549999997,
    "Trade_Date":"22 Jun 26",
    "Pct_Change":-3.87,
    "Fetched_At":"2026-06-22 12:57:23"
  },
  {
    "Company":"SUNUASSUR",
    "Prev_Close":3.61,
    "Opening_Price":3.61,
    "High":0.0,
    "Low":0.0,
    "Close":0.0,
    "Change":0.0,
    "Trades":26.0,
    "Volume":139438.0,
    "Value":534534.87,
    "Trade_Date":"22 Jun 26",
    "Pct_Change":0.0,
    "Fetched_At":"2026-06-22 12:57:23"
  },
  {
    "Company":"TANTALIZER",
    "Prev_Close":4.4,
    "Opening_Price":4.4,
    "High":4.65,
    "Low":4.36,
    "Close":4.38,
    "Change":-0.02,
    "Trades":375.0,
    "Volume":6369090.0,
    "Value":28024013.2199999988,
    "Trade_Date":"22 Jun 26",
    "Pct_Change":-0.45,
    "Fetched_At":"2026-06-22 12:57:23"
  },
  {
    "Company":"THOMASWY",
    "Prev_Close":2.75,
    "Opening_Price":2.75,
    "High":0.0,
    "Low":0.0,
    "Close":0.0,
    "Change":0.0,
    "Trades":0.0,
    "Volume":0.0,
    "Value":0.0,
    "Trade_Date":"22 Jun 26",
    "Pct_Change":0.0,
    "Fetched_At":"2026-06-22 12:57:23"
  },
  {
    "Company":"TIP",
    "Prev_Close":28.9,
    "Opening_Price":28.9,
    "High":28.85,
    "Low":28.5,
    "Close":28.5,
    "Change":-0.4,
    "Trades":1061.0,
    "Volume":5516218.0,
    "Value":159735173.1999999881,
    "Trade_Date":"22 Jun 26",
    "Pct_Change":-1.38,
    "Fetched_At":"2026-06-22 12:57:23"
  },
  {
    "Company":"TOTAL",
    "Prev_Close":640.0,
    "Opening_Price":640.0,
    "High":0.0,
    "Low":0.0,
    "Close":0.0,
    "Change":0.0,
    "Trades":39.0,
    "Volume":22328.0,
    "Value":12860928.0,
    "Trade_Date":"22 Jun 26",
    "Pct_Change":0.0,
    "Fetched_At":"2026-06-22 12:57:23"
  },
  {
    "Company":"TRANSCOHOT",
    "Prev_Close":223.3,
    "Opening_Price":223.3,
    "High":0.0,
    "Low":0.0,
    "Close":0.0,
    "Change":0.0,
    "Trades":106.0,
    "Volume":26419.0,
    "Value":5831156.5999999996,
    "Trade_Date":"22 Jun 26",
    "Pct_Change":0.0,
    "Fetched_At":"2026-06-22 12:57:23"
  },
  {
    "Company":"TRANSCORP",
    "Prev_Close":44.0,
    "Opening_Price":44.0,
    "High":43.5,
    "Low":41.2,
    "Close":41.2,
    "Change":-2.8,
    "Trades":364.0,
    "Volume":2203871.0,
    "Value":93102796.549999997,
    "Trade_Date":"22 Jun 26",
    "Pct_Change":-6.36,
    "Fetched_At":"2026-06-22 12:57:23"
  },
  {
    "Company":"TRANSEXPR",
    "Prev_Close":4.48,
    "Opening_Price":4.48,
    "High":0.0,
    "Low":0.0,
    "Close":0.0,
    "Change":0.0,
    "Trades":42.0,
    "Volume":983752.0,
    "Value":4124751.23,
    "Trade_Date":"22 Jun 26",
    "Pct_Change":0.0,
    "Fetched_At":"2026-06-22 12:57:23"
  },
  {
    "Company":"TRANSPOWER",
    "Prev_Close":245.5,
    "Opening_Price":245.5,
    "High":0.0,
    "Low":0.0,
    "Close":0.0,
    "Change":0.0,
    "Trades":33.0,
    "Volume":13024.0,
    "Value":2878304.0,
    "Trade_Date":"22 Jun 26",
    "Pct_Change":0.0,
    "Fetched_At":"2026-06-22 12:57:23"
  },
  {
    "Company":"TRIPPLEG",
    "Prev_Close":3.36,
    "Opening_Price":3.36,
    "High":0.0,
    "Low":0.0,
    "Close":0.0,
    "Change":0.0,
    "Trades":32.0,
    "Volume":136173.0,
    "Value":424058.95,
    "Trade_Date":"22 Jun 26",
    "Pct_Change":0.0,
    "Fetched_At":"2026-06-22 12:57:23"
  },
  {
    "Company":"UACN",
    "Prev_Close":185.0,
    "Opening_Price":185.0,
    "High":0.0,
    "Low":0.0,
    "Close":0.0,
    "Change":0.0,
    "Trades":222.0,
    "Volume":374154.0,
    "Value":67207958.049999997,
    "Trade_Date":"22 Jun 26",
    "Pct_Change":0.0,
    "Fetched_At":"2026-06-22 12:57:23"
  },
  {
    "Company":"UBA",
    "Prev_Close":39.5,
    "Opening_Price":39.5,
    "High":41.65,
    "Low":39.55,
    "Close":39.55,
    "Change":0.05,
    "Trades":1537.0,
    "Volume":21219865.0,
    "Value":848801534.8500000238,
    "Trade_Date":"22 Jun 26",
    "Pct_Change":0.13,
    "Fetched_At":"2026-06-22 12:57:23"
  },
  {
    "Company":"UCAP",
    "Prev_Close":18.0,
    "Opening_Price":18.0,
    "High":18.0,
    "Low":17.9,
    "Close":18.0,
    "Change":0.0,
    "Trades":313.0,
    "Volume":2888745.0,
    "Value":51784783.8999999985,
    "Trade_Date":"22 Jun 26",
    "Pct_Change":0.0,
    "Fetched_At":"2026-06-22 12:57:23"
  },
  {
    "Company":"UHOMREIT",
    "Prev_Close":70.0,
    "Opening_Price":70.0,
    "High":0.0,
    "Low":0.0,
    "Close":0.0,
    "Change":0.0,
    "Trades":42.0,
    "Volume":54043.0,
    "Value":4086997.3500000001,
    "Trade_Date":"22 Jun 26",
    "Pct_Change":0.0,
    "Fetched_At":"2026-06-22 12:57:23"
  },
  {
    "Company":"UNILEVER",
    "Prev_Close":140.0,
    "Opening_Price":140.0,
    "High":0.0,
    "Low":0.0,
    "Close":0.0,
    "Change":0.0,
    "Trades":92.0,
    "Volume":82603.0,
    "Value":10407978.0,
    "Trade_Date":"22 Jun 26",
    "Pct_Change":0.0,
    "Fetched_At":"2026-06-22 12:57:23"
  },
  {
    "Company":"UNIONDICON",
    "Prev_Close":23.75,
    "Opening_Price":23.75,
    "High":0.0,
    "Low":0.0,
    "Close":0.0,
    "Change":0.0,
    "Trades":4.0,
    "Volume":466.0,
    "Value":9972.4,
    "Trade_Date":"22 Jun 26",
    "Pct_Change":0.0,
    "Fetched_At":"2026-06-22 12:57:23"
  },
  {
    "Company":"UNITYBNK",
    "Prev_Close":1.51,
    "Opening_Price":1.51,
    "High":0.0,
    "Low":0.0,
    "Close":0.0,
    "Change":0.0,
    "Trades":0.0,
    "Volume":0.0,
    "Value":0.0,
    "Trade_Date":"22 Jun 26",
    "Pct_Change":0.0,
    "Fetched_At":"2026-06-22 12:57:23"
  },
  {
    "Company":"UNIVINSURE",
    "Prev_Close":1.03,
    "Opening_Price":1.03,
    "High":1.08,
    "Low":1.03,
    "Close":1.08,
    "Change":0.05,
    "Trades":92.0,
    "Volume":5986266.0,
    "Value":6214028.3099999996,
    "Trade_Date":"22 Jun 26",
    "Pct_Change":4.85,
    "Fetched_At":"2026-06-22 12:57:23"
  },
  {
    "Company":"UPDC [BLS]",
    "Prev_Close":3.8,
    "Opening_Price":3.8,
    "High":3.8,
    "Low":3.8,
    "Close":3.8,
    "Change":0.0,
    "Trades":94.0,
    "Volume":3578200.0,
    "Value":13572636.25,
    "Trade_Date":"22 Jun 26",
    "Pct_Change":0.0,
    "Fetched_At":"2026-06-22 12:57:23"
  },
  {
    "Company":"UPDCREIT",
    "Prev_Close":10.0,
    "Opening_Price":10.0,
    "High":10.0,
    "Low":10.0,
    "Close":10.0,
    "Change":0.0,
    "Trades":218.0,
    "Volume":1774291.0,
    "Value":17785471.6999999993,
    "Trade_Date":"22 Jun 26",
    "Pct_Change":0.0,
    "Fetched_At":"2026-06-22 12:57:23"
  },
  {
    "Company":"UPL",
    "Prev_Close":5.45,
    "Opening_Price":5.45,
    "High":0.0,
    "Low":0.0,
    "Close":0.0,
    "Change":0.0,
    "Trades":39.0,
    "Volume":93126.0,
    "Value":513990.55,
    "Trade_Date":"22 Jun 26",
    "Pct_Change":0.0,
    "Fetched_At":"2026-06-22 12:57:23"
  },
  {
    "Company":"VERITASKAP",
    "Prev_Close":1.49,
    "Opening_Price":1.49,
    "High":1.49,
    "Low":1.4,
    "Close":1.47,
    "Change":-0.02,
    "Trades":120.0,
    "Volume":3637746.0,
    "Value":5352551.8799999999,
    "Trade_Date":"22 Jun 26",
    "Pct_Change":-1.34,
    "Fetched_At":"2026-06-22 12:57:23"
  },
  {
    "Company":"VFDGROUP",
    "Prev_Close":10.5,
    "Opening_Price":10.5,
    "High":0.0,
    "Low":0.0,
    "Close":0.0,
    "Change":0.0,
    "Trades":158.0,
    "Volume":485630.0,
    "Value":4988347.7000000002,
    "Trade_Date":"22 Jun 26",
    "Pct_Change":0.0,
    "Fetched_At":"2026-06-22 12:57:23"
  },
  {
    "Company":"VITAFOAM",
    "Prev_Close":189.0,
    "Opening_Price":189.0,
    "High":0.0,
    "Low":0.0,
    "Close":0.0,
    "Change":0.0,
    "Trades":156.0,
    "Volume":52437.0,
    "Value":8974058.9499999993,
    "Trade_Date":"22 Jun 26",
    "Pct_Change":0.0,
    "Fetched_At":"2026-06-22 12:57:23"
  },
  {
    "Company":"WAPCO",
    "Prev_Close":315.1,
    "Opening_Price":315.1,
    "High":316.0,
    "Low":316.0,
    "Close":316.0,
    "Change":0.9,
    "Trades":988.0,
    "Volume":1710907.0,
    "Value":541966667.2999999523,
    "Trade_Date":"22 Jun 26",
    "Pct_Change":0.29,
    "Fetched_At":"2026-06-22 12:57:23"
  },
  {
    "Company":"WAPIC",
    "Prev_Close":2.5,
    "Opening_Price":2.5,
    "High":0.0,
    "Low":0.0,
    "Close":0.0,
    "Change":0.0,
    "Trades":80.0,
    "Volume":602600.0,
    "Value":1518699.79,
    "Trade_Date":"22 Jun 26",
    "Pct_Change":0.0,
    "Fetched_At":"2026-06-22 12:57:23"
  },
  {
    "Company":"WEMABANK",
    "Prev_Close":30.0,
    "Opening_Price":30.0,
    "High":0.0,
    "Low":0.0,
    "Close":0.0,
    "Change":0.0,
    "Trades":544.0,
    "Volume":903660.0,
    "Value":26084523.6000000015,
    "Trade_Date":"22 Jun 26",
    "Pct_Change":0.0,
    "Fetched_At":"2026-06-22 12:57:23"
  },
  {
    "Company":"ZENITHBANK",
    "Prev_Close":110.0,
    "Opening_Price":110.0,
    "High":114.9,
    "Low":113.5,
    "Close":114.9,
    "Change":4.9,
    "Trades":3605.0,
    "Volume":19493079.0,
    "Value":2227406589.6999998093,
    "Trade_Date":"22 Jun 26",
    "Pct_Change":4.45,
    "Fetched_At":"2026-06-22 12:57:23"
  },
  {
    "Company":"ZICHIS",
    "Prev_Close":26.0,
    "Opening_Price":26.0,
    "High":0.0,
    "Low":0.0,
    "Close":0.0,
    "Change":0.0,
    "Trades":365.0,
    "Volume":1741752.0,
    "Value":42945441.049999997,
    "Trade_Date":"22 Jun 26",
    "Pct_Change":0.0,
    "Fetched_At":"2026-06-22 12:57:23"
  }
]